ecbrates/__init__.py
ecbrates/cache.py
ecbrates/cli.py
ecbrates/core.py
ecbrates/datasource.py
ecbrates/exceptions.py
ecbrates-0.1.4.dist-info/METADATA
ecbrates-0.1.4.dist-info/WHEEL
ecbrates-0.1.4.dist-info/entry_points.txt
ecbrates-0.1.4.dist-info/RECORD
