Metadata-Version: 2.4
Name: ecbrates
Version: 0.1.4
Summary: Unofficial package: European Central Bank Foreign Exchange Rates
Requires-Python: >=3.10
Requires-Dist: diskcache
Requires-Dist: freezegun
Requires-Dist: holidays
Requires-Dist: requests
Provides-Extra: cli
Requires-Dist: typer; extra == 'cli'
Provides-Extra: test
Requires-Dist: pytest; extra == 'test'
Requires-Dist: pytest-benchmark; extra == 'test'
Requires-Dist: pytest-cov; extra == 'test'
